calculator3220.py
calculator3220-0.1.5.dist-info/LICENSE
calculator3220-0.1.5.dist-info/WHEEL
calculator3220-0.1.5.dist-info/METADATA
calculator3220-0.1.5.dist-info/RECORD
