Metadata-Version: 2.1
Name: calculator3220
Version: 0.1.5
Summary: Simple math calculator
Author-email: Gvidas <gviidas@gmail.com>
Classifier: License :: OSI Approved :: MIT License
